setup.cfg
setup.py
src/django_flashcard.egg-info/PKG-INFO
src/django_flashcard.egg-info/SOURCES.txt
src/django_flashcard.egg-info/dependency_links.txt
src/django_flashcard.egg-info/entry_points.txt
src/django_flashcard.egg-info/requires.txt
src/django_flashcard.egg-info/top_level.txt
src/flashcard/__init__.py
src/flashcard/admin.py
src/flashcard/algorithm.py
src/flashcard/forms.py
src/flashcard/models.py
src/flashcard/testsettings.py
src/flashcard/urls.py
src/flashcard/views.py
src/flashcard/tests/__init__.py
src/flashcard/tests/tests.py